zigpy_zboss/__init__.py
zigpy_zboss/api.py
zigpy_zboss/checksum.py
zigpy_zboss/config.py
zigpy_zboss/debug.py
zigpy_zboss/exceptions.py
zigpy_zboss/frames.py
zigpy_zboss/logger.py
zigpy_zboss/nvram.py
zigpy_zboss/uart.py
zigpy_zboss/utils.py
zigpy_zboss/commands/__init__.py
zigpy_zboss/commands/af.py
zigpy_zboss/commands/aps.py
zigpy_zboss/commands/ncp_config.py
zigpy_zboss/commands/nwk_mgmt.py
zigpy_zboss/commands/security.py
zigpy_zboss/commands/zdo.py
zigpy_zboss/tools/__init__.py
zigpy_zboss/tools/config.py
zigpy_zboss/tools/factory_reset_ncp.py
zigpy_zboss/tools/get_ncp_version.py
zigpy_zboss/tools/log2pcap.py
zigpy_zboss/types/__init__.py
zigpy_zboss/types/basic.py
zigpy_zboss/types/commands.py
zigpy_zboss/types/cstruct.py
zigpy_zboss/types/named.py
zigpy_zboss/types/nvids.py
zigpy_zboss/types/structs.py
zigpy_zboss/zigbee/__init__.py
zigpy_zboss/zigbee/application.py
zigpy_zboss/zigbee/device.py
zigpy_zboss-1.2.0.dist-info/COPYING
zigpy_zboss-1.2.0.dist-info/LICENSE
zigpy_zboss-1.2.0.dist-info/METADATA
zigpy_zboss-1.2.0.dist-info/WHEEL
zigpy_zboss-1.2.0.dist-info/top_level.txt
zigpy_zboss-1.2.0.dist-info/RECORD
