Metadata-Version: 2.1
Name: zigpy-zboss
Version: 1.2.0
Summary: A library for zigpy which communicates with Nordic nRF52 radios
Home-page: https://github.com/kardia-as/zigpy-zboss
Author: Damien Kastner
Author-email: damien.kastner@kardia.no
License: GPL-3.0
Requires-Python: >=3.7
License-File: LICENSE
License-File: COPYING
Requires-Dist: zigpy >=0.60.2
Requires-Dist: async-timeout
Requires-Dist: voluptuous
Requires-Dist: coloredlogs
Requires-Dist: jsonschema
Provides-Extra: testing
Requires-Dist: pytest >=5.4.5 ; extra == 'testing'
Requires-Dist: pytest-asyncio >=0.12.0 ; extra == 'testing'
Requires-Dist: pytest-timeout ; extra == 'testing'
Requires-Dist: pytest-mock ; extra == 'testing'
Requires-Dist: pytest-cov ; extra == 'testing'
Requires-Dist: coveralls ; extra == 'testing'
Requires-Dist: asynctest ; (python_version < "3.8.0") and extra == 'testing'
